{"simulationFinished":false,"totalTime":6.728330135345459,"numberOfSections":4,"numberOfCPSections":1,"numberOfNodes":4,"numberOfEdges":3,"numberOfPeople":12,"pathsImage":"","sectionInfos":[{"ID":0,"isCP":false,"totalTime":0.09973859786987305,"worstLOS":"B","mediaLOS":"B"},{"ID":1,"isCP":true,"totalTime":6.728330135345459,"worstLOS":"A","mediaLOS":"A"},{"ID":2,"isCP":false,"totalTime":0.0,"worstLOS":"B","mediaLOS":"A"},{"ID":3,"isCP":false,"totalTime":0.0,"worstLOS":"A","mediaLOS":"A"}],"personInfos":[{"ID":0,"CPID":1,"totalTime":6.728330135345459},{"ID":1,"CPID":2,"totalTime":6.725576877593994},{"ID":2,"CPID":0,"totalTime":0.09973859786987305},{"ID":3,"CPID":2,"totalTime":0.11564189940690994},{"ID":4,"CPID":2,"totalTime":0.14871540665626527},{"ID":5,"CPID":0,"totalTime":0.09973859786987305},{"ID":6,"CPID":1,"totalTime":6.728330135345459},{"ID":7,"CPID":0,"totalTime":0.09973859786987305},{"ID":8,"CPID":2,"totalTime":6.524052619934082},{"ID":9,"CPID":0,"totalTime":0.09973859786987305},{"ID":10,"CPID":0,"totalTime":0.09973859786987305},{"ID":11,"CPID":2,"totalTime":4.658790588378906}]}